Workbook

Sheet Sommaire
B2: Questionnaire de qualification IA — TPE / PME
B4: Pour chaque ligne : sélectionner la valeur dans la liste déroulante. Pastille verte = brique enrichissable par l'IA.
B6: Légende : | C6: ● | D6: Compatible / enrichissable IA
B8: Chapitre | C8: Nb éléments | D8: Dont IA | E8: % IA | F8: Complétude
B9: 1. Infrastructure matérielle | C9: 8 | D9: 6 | E9: =D9/C9 -> 0.75 | F9: =COUNTA('1. Infrastructure matérielle'!E6:E13)&" / 8" -> 0 / 8
B10: 2. Connectivité | C10: 4 | D10: 3 | E10: =D10/C10 -> 0.75 | F10: =COUNTA('2. Connectivité'!E6:E9)&" / 4" -> 0 / 4
B11: 3. Logiciels & applications | C11: 5 | D11: 5 | E11: =D11/C11 -> 1 | F11: =COUNTA('3. Logiciels & applications'!E6:E10)&" / 5" -> 0 / 5
B12: 4. Cloud | C12: 4 | D12: 3 | E12: =D12/C12 -> 0.75 | F12: =COUNTA('4. Cloud'!E6:E9)&" / 4" -> 0 / 4
B13: 5. Cybersécurité | C13: 8 | D13: 7 | E13: =D13/C13 -> 0.875 | F13: =COUNTA('5. Cybersécurité'!E6:E13)&" / 8" -> 0 / 8
B14: 6. Données & conformité | C14: 5 | D14: 5 | E14: =D14/C14 -> 1 | F14: =COUNTA('6. Données & conformité'!E6:E10)&" / 5" -> 0 / 5
B15: 7. Présence en ligne & marketing | C15: 5 | D15: 4 | E15: =D15/C15 -> 0.8 | F15: =COUNTA('7. Présence en ligne & marketin'!E6:E10)&" / 5" -> 0 / 5
B16: 8. Mobilité & télétravail | C16: 4 | D16: 3 | E16: =D16/C16 -> 0.75 | F16: =COUNTA('8. Mobilité & télétravail'!E6:E9)&" / 4" -> 0 / 4
B17: 9. Services & exploitation | C17: 5 | D17: 5 | E17: =D17/C17 -> 1 | F17: =COUNTA('9. Services & exploitation'!E6:E10)&" / 5" -> 0 / 5
B18: 10. Innovation & transformation | C18: 4 | D18: 4 | E18: =D18/C18 -> 1 | F18: =COUNTA('10. Innovation & transformation'!E6:E9)&" / 4" -> 0 / 4
B19: 11. Gouvernance & humain | C19: 4 | D19: 3 | E19: =D19/C19 -> 0.75 | F19: =COUNTA('11. Gouvernance & humain'!E6:E9)&" / 4" -> 0 / 4
B20: TOTAL | C20: 56 | D20: 48 | E20: =D20/C20 -> 0.85714286
B23: ℹ Les listes de valeurs sont modifiables dans l'onglet « Listes » (à la fin du classeur).

Sheet Listes
A1: Listes de valeurs (référentiel)
A3: L_postes | B3: L_serveurs | C3: L_stockage | D3: L_reseau | E3: L_firewall | F3: L_onduleur | G3: L_periph | H3: L_av | I3: L_internet | J3: L_lan | K3: L_vpn | L3: L_tel | M3: L_office | N3: L_messagerie | O3: L_erp | P3: L_metier | Q3: L_ged | R3: L_saas | S3: L_iaas | T3: L_heberg | U3: L_backup | V3: L_av_endpoint | W3: L_filt | X3: L_pra | Y3: L_mfa | Z3: L_pwd | AA3: L_audit | AB3: L_sensi | AC3: L_conf | AD3: L_bi | AE3: L_rgpd | AF3: L_archivage | AG3: L_facture | AH3: L_legal | AI3: L_domaine | AJ3: L_site | AK3: L_seo | AL3: L_rs | AM3: L_emailing | AN3: L_mobile | AO3: L_mdm | AP3: L_remote | AQ3: L_virtualposte | AR3: L_infog | AS3: L_helpdesk | AT3: L_tma | AU3: L_patch | AV3: L_licences | AW3: L_iagen | AX3: L_auto | AY3: L_iot | AZ3: L_demat | BA3: L_charte | BB3: L_sdsi | BC3: L_form | BD3: L_contrat
A4: Aucun | B4: Aucun (full cloud) | C4: Aucun stockage centralisé | D4: Box opérateur seule | E4: Aucun (box opérateur) | F4: Aucun | G4: Aucun | H4: Aucun | I4: ADSL / VDSL | J4: Réseau plat (un seul réseau) | K4: Aucun | L4: RTC analogique (en sursis) | M4: Aucune | N4: Aucune messagerie pro | O4: Aucun | P4: Aucun | Q4: Aucune | R4: Aucun SaaS | S4: Aucun | T4: Aucun site | U4: Aucune sauvegarde | V4: Windows Defender seul | W4: Box opérateur uniquement | X4: Aucune sauvegarde | Y4: Aucun MFA | Z4: Aucun (post-it / Excel) | AA4: Aucun audit | AB4: Aucune sensibilisation | AC4: Aucune démarche | AD4: Aucun (Excel basique) | AE4: Aucune action | AF4: Aucun | AG4: Aucune préparation | AH4: Aucune | AI4: Aucun | AJ4: Aucun | AK4: Aucune action | AL4: Aucun | AM4: Aucun | AN4: Aucun | AO4: Aucun MDM | AP4: Aucun | AQ4: Aucun | AR4: 100% interne | AS4: Aucun | AT4: Aucune | AU4: Manuel | AV4: Tableur Excel | AW4: Aucune | AX4: Aucune | AY4: Aucun | AZ4: Aucune | BA4: Aucune | BB4: Aucun | BC4: Aucune | BD4: Aucun
A5: Tour fixe Windows | B5: Serveur physique unique | C5: NAS Synology | D5: Switch non managé | E5: Stormshield | F5: 1 onduleur poste | G5: Imprimante personnelle | H5: Webcam basique | I5: Fibre FTTH grand public | J5: Plusieurs SSID | K5: VPN site-à-site IPsec | L5: Trunk SIP | M5: Microsoft 365 Business | N5: Email OVH (IMAP) | O5: Odoo Online | P5: 1 logiciel métier vertical | Q5: SharePoint / OneDrive | R5: Quelques outils SaaS | S5: Microsoft Azure | T5: OVH | U5: Disque externe | V5: Antivirus grand public | W5: UTM Stormshield | X5: Disque externe seul | Y5: MFA partiel (admins) | Z5: Navigateur | AA5: Audit interne ponctuel | AB5: Sensibilisation ponctuelle | AC5: RGPD entamée | AD5: Excel avancé | AE5: Registre des traitements fait | AF5: Archivage papier | AG5: En cours | AH5: Existantes mais anciennes | AI5: 1 domaine | AJ5: Vitrine simple | AK5: Google Business Profile rempli | AL5: LinkedIn entreprise | AM5: Mailchimp | AN5: BYOD (matériel perso) | AO5: Microsoft Intune | AP5: VPN classique | AQ5: RDS local sur serveur | AR5: Régie ponctuelle | AS5: Support interne | AT5: Contrat éditeur | AU5: WSUS | AV5: Outil ITAM dédié | AW5: ChatGPT Free | AX5: Macros Excel / VBA | AY5: Quelques capteurs (température, présence) | AZ5: Partielle | BA5: Existante mais non signée | BB5: Plan annuel informel | BC5: Formations ad-hoc | BD5: Standards éditeur
A6: Portable Windows | B6: Plusieurs serveurs physiques | C6: NAS QNAP | D6: Switch managé (Aruba/Cisco/Ubiquiti) | E6: Fortinet (FortiGate) | F6: Onduleur serveur | G6: MFP en propriété | H6: Salle de visio équipée | I6: Fibre pro FTTO | J6: VLAN partiel (invités séparés) | K6: VPN nomades (OpenVPN/WireGuard/IPsec) | L6: Centrex 3CX | M6: Microsoft Office perpétuel / OEM | N6: Email Ionos / Gandi (IMAP) | O6: Odoo Enterprise self-hosted | P6: Plusieurs logiciels métier | Q6: DocuWare | R6: Stack majoritairement SaaS | S6: AWS | T6: Ionos | U6: NAS local uniquement | V6: ESET | W6: UTM Fortinet | X6: NAS local seul | Y6: MFA généralisé | Z6: Bitwarden | AA6: Audit externe annuel | AB6: Plateforme dédiée (Riot/Mantra/KnowBe4/Conscio) | AC6: RGPD conforme + DPO | AD6: Power BI | AE6: DPO interne | AF6: Archivage électronique simple | AG6: PDP choisie (à préciser) | AH6: À jour | AI6: Plusieurs domaines | AJ6: Vitrine WordPress | AK6: SEO actif | AL6: Facebook | AM6: Brevo (ex-Sendinblue) | AN6: COPE (matériel pro à usage perso autorisé) | AO6: Apple Business Manager | AP6: ZTNA | AQ6: Azure Virtual Desktop | AR6: Forfait infogérance | AS6: Support externalisé | AT6: TMA externalisée | AU6: Outil dédié (PDQ / Action1 / ManageEngine) | AV6: Reseller / CSP partenaire (XEFI / RESOLOG) | AW6: ChatGPT Plus / Team | AX6: Power Automate | AY6: Maintenance prédictive | AZ6: Complète | BA6: Signée par les employés | BB6: Plan annuel formalisé | BC6: Plan de formation annuel | BD6: Contrats sur mesure
A7: Mac (iMac/MacBook) | B7: Virtualisé Hyper-V | C7: NAS autre marque | D7: Wi-Fi grand public | E7: Sophos | F7: Plusieurs onduleurs supervisés | G7: MFP en location / contrat | H7: Affichage dynamique | I7: SDSL | J7: VLAN complet (data/voix/IoT/invités) | K7: ZTNA (Zero Trust) | L7: Centrex Wildix | M7: Google Workspace | N7: Exchange Online (Microsoft 365) | O7: Odoo Community | P7: Développement spécifique interne | Q7: Zeendoc | R7: 100% SaaS | S7: OVHcloud | T7: Gandi | U7: Veeam | V7: Bitdefender | W7: UTM Sophos | X7: Cloud uniquement | Y7: SSO Entra ID (Azure AD) | Z7: 1Password | AA7: Pentest régulier | AB7: Simulations de phishing régulières | AC7: ISO 27001 | AD7: Tableau | AE7: DPO externe | AF7: Archivage à valeur probante (Locarchives/Arkhinéo) | AG7: Conforme via Odoo | AH7: Rédigées par avocat / juriste | AI7: Inconnu | AJ7: E-commerce Prestashop | AK7: SEA actif (Google Ads) | AL7: Instagram | AM7: HubSpot | AN7: Flotte pro dédiée | AO7: Google Workspace MDM | AP7: RDP via VPN | AQ7: Windows 365 | AR7: Infogérance complète 24/7 | AS7: Hotline éditeur uniquement | AT7: Dev interne | AU7: RMM (NinjaOne / Datto / ConnectWise) | AV7: Mix | AW7: ChatGPT Enterprise | AX7: n8n | AY7: Plateforme IoT dédiée | AZ7: Inconnu | BA7: Politique de sécurité formalisée | BB7: Roadmap 3-5 ans | BC7: Plateforme e-learning | BD7: Avocat / DPO dédié
A8: Mix Windows + Mac | B8: Virtualisé VMware | C8: Serveur de fichiers Windows | D8: Wi-Fi pro (UniFi/Aruba/Meraki/Omada) | E8: WatchGuard | F8: Inconnu | G8: Solution GED | H8: Écrans interactifs | I8: 4G / 5G | J8: Inconnu | K8: SD-WAN | L8: Centrex Sewan / Centile | M8: LibreOffice / OpenOffice | N8: Exchange On-Premise | O8: Sage 50 / 100 | P8: Inconnu | Q8: M-Files | R8: Inconnu | S8: Scaleway | T8: Hostinger | U8: Datto | V8: Kaspersky | W8: Filtrage DNS (Umbrella/NextDNS/DNSFilter) | X8: Règle 3-2-1 complète | Y8: SSO Google Workspace | Z8: LastPass | AA8: Bug bounty | AB8: Inconnu | AC8: NIS 2 concerné | AD8: Qlik | AE8: Inconnu | AF8: Inconnu | AG8: Conforme via éditeur ERP | AH8: Inconnu | AJ8: E-commerce WooCommerce | AK8: Agence web dédiée | AL8: TikTok | AM8: ActiveCampaign | AN8: Mix | AO8: Jamf | AP8: TeamViewer / AnyDesk | AQ8: Citrix | AR8: XEFI | AS8: Inconnu | AT8: Inconnu | AU8: Inconnu | AV8: Inconnu | AW8: Microsoft 365 Copilot | AX8: Zapier / Make | AY8: Inconnu | BA8: Inconnu | BB8: Inconnu | BC8: Sensibilisation IA spécifique | BD8: Inconnu
A9: Thin client | B9: Virtualisé Proxmox | C9: SAN dédié | D9: Architecture VLAN complète | E9: pfSense / OPNsense | G9: TPE de paiement | H9: Mix | I9: Lien principal + secours 4G/5G | K9: Mix | L9: Centrex Ringover / Aircall | M9: Mix | N9: Google Workspace (Gmail) | O9: Sage X3 | Q9: Open Bee | S9: Google Cloud | T9: Auto-hébergement | U9: Acronis | V9: EDR SentinelOne | W9: Anti-spam Vade | X9: PRA documenté | Y9: IAM dédié (Okta/Auth0) | Z9: Dashlane | AA9: Inconnu | AC9: NIS 2 conforme | AD9: Looker Studio | AG9: Conforme via plateforme dédiée | AJ9: E-commerce Shopify | AK9: Inconnu | AL9: Plusieurs réseaux | AM9: Mailjet | AN9: Inconnu | AO9: Ivanti / MobileIron | AP9: Mix | AQ9: VMware Horizon | AR9: Autre prestataire | AW9: Claude (Anthropic) | AX9: Workflows ERP (Odoo, etc.) | BC9: Inconnu
A10: Chromebook | B10: Hyperconvergé (Nutanix/vSAN) | C10: OneDrive / SharePoint | D10: Mix | E10: Cisco / Meraki | G10: Douchettes / scanners code-barre | H10: Inconnu | I10: Mix | K10: Inconnu | L10: IPBX on-premise (3CX/Yeastar/Asterisk) | M10: Inconnu | N10: Zimbra | O10: EBP | Q10: Yousign | S10: Mix multi-cloud | T10: Wix / Squarespace / WordPress.com | U10: Wasabi / Backblaze B2 | V10: EDR CrowdStrike | W10: Anti-spam Mailinblack | X10: PRA documenté ET testé | Y10: Inconnu | Z10: KeePass | AC10: Inconnu | AD10: Metabase | AG10: Inconnu | AJ10: E-commerce Magento | AL10: Community manager dédié | AM10: Marketing automation Odoo | AO10: Inconnu | AP10: Inconnu | AQ10: Inconnu | AR10: Mix interne / externe | AW10: Gemini | AX10: Mix
A11: Autre | B11: NAS faisant office de serveur | C11: Google Drive | D11: Inconnu | E11: Autre | G11: Mix | I11: Inconnu | L11: Téléphonie box opérateur | N11: Bluemind | O11: Cegid | Q11: DocuSign | S11: Inconnu | T11: Inconnu | U11: Sauvegarde NAS vers cloud | V11: EDR Sophos Intercept X | W11: Anti-spam Altospam | X11: PCA en place | Z11: Inconnu | AD11: BI intégré à l'ERP | AJ11: Site sur mesure | AL11: Inconnu | AM11: Mix | AR11: Inconnu | AW11: Mistral / Le Chat | AX11: Inconnu
A12: Inconnu | B12: Cloud uniquement (Azure/AWS/OVH) | C12: Mix local + cloud | E12: Inconnu | G12: Inconnu | L12: Mobiles uniquement | N12: Mailbox grand public (Orange/Free/Gmail perso) | O12: Dynamics 365 / Business Central | Q12: Universign | U12: Backup M365 (AvePoint/Veeam/SkyKick) | V12: Microsoft Defender for Endpoint | W12: Anti-spam Microsoft Defender | X12: Inconnu | AD12: Inconnu | AJ12: Réseaux sociaux uniquement | AM12: Inconnu | AW12: Auto-hébergée (Ollama / OpenWebUI)
B13: Mix | C13: Inconnu | L13: Mix | N13: Mix | O13: SAP Business One | Q13: Adobe Sign | U13: Mix | V13: XDR / SOC managé | W13: Mix | AJ13: Inconnu | AW13: Mix
B14: Inconnu | L14: Inconnu | N14: Inconnu | O14: SAP S/4HANA | Q14: Mix | U14: Inconnu | V14: Inconnu | W14: Inconnu | AW14: Inconnu
O15: Salesforce | Q15: Inconnu
O16: HubSpot
O17: Pipedrive
O18: Excel / manuel
O19: Mix de plusieurs outils
O20: Autre
O21: Inconnu

Sheet 1. Infrastructure matérielle
B2: 1. Infrastructure matérielle
B5: # | C5: Élément | D5: IA | E5: Réponse client | F5: Précision / autre | G5: Apport IA
B6: 1 | C6: Postes de travail (fixes, portables, Mac) | D6: ● | G6: Copilot+ PC, NPU, IA locale
B7: 2 | C7: Serveurs (physiques, virtualisés, hyperconvergés)
B8: 3 | C8: Stockage : NAS, SAN, baies | D8: ● | G8: Classification et reconnaissance auto
B9: 4 | C9: Équipements réseau : switchs, Wi-Fi, routeurs | D9: ● | G9: AIOps, optimisation Wi-Fi
B10: 5 | C10: Pare-feu | D10: ● | G10: Détection comportementale par IA
B11: 6 | C11: Onduleurs
B12: 7 | C12: Périphériques : MFP, scanners, TPE, douchettes | D12: ● | G12: OCR, extraction intelligente
B13: 8 | C13: Audiovisuel : visio, écrans, affichage dynamique | D13: ● | G13: Transcription, sous-titres, cadrage auto
B15: Synthèse | E15: =COUNTA(E6:E13) -> 0 | F15: réponses sur 8 (dont 6 IA — 75%)
B17: ← Retour au sommaire

Sheet 2. Connectivité
B2: 2. Connectivité
B5: # | C5: Élément | D5: IA | E5: Réponse client | F5: Précision / autre | G5: Apport IA
B6: 1 | C6: Accès Internet
B7: 2 | C7: Réseau LAN / Wi-Fi pro / VLAN | D7: ● | G7: Supervision et auto-tuning IA
B8: 3 | C8: VPN / SD-WAN / ZTNA | D8: ● | G8: Routage intelligent, scoring
B9: 4 | C9: Téléphonie IP / standard / mobiles | D9: ● | G9: SVI conversationnel, voicebots, transcription
B11: Synthèse | E11: =COUNTA(E6:E9) -> 0 | F11: réponses sur 4 (dont 3 IA — 75%)
B13: ← Retour au sommaire

Sheet 3. Logiciels & applications
B2: 3. Logiciels & applications
B5: # | C5: Élément | D5: IA | E5: Réponse client | F5: Précision / autre | G5: Apport IA
B6: 1 | C6: Suite bureautique | D6: ● | G6: Copilot M365, Gemini
B7: 2 | C7: Messagerie pro + collaboration | D7: ● | G7: Résumés, rédaction, recherche sémantique
B8: 3 | C8: ERP / CRM / compta / paie / RH | D8: ● | G8: Odoo AI, Sage Copilot, prévisions, scoring
B9: 4 | C9: Logiciels métiers verticaux | D9: ● | G9: IA intégrée par les éditeurs
B10: 5 | C10: GED / signature électronique / coffre-fort | D10: ● | G10: Classement, extraction, recherche IA
B12: Synthèse | E12: =COUNTA(E6:E10) -> 0 | F12: réponses sur 5 (dont 5 IA — 100%)
B14: ← Retour au sommaire

Sheet 4. Cloud
B2: 4. Cloud
B5: # | C5: Élément | D5: IA | E5: Réponse client | F5: Précision / autre | G5: Apport IA
B6: 1 | C6: SaaS | D6: ● | G6: IA native dans la plupart des suites
B7: 2 | C7: IaaS / PaaS | D7: ● | G7: Azure OpenAI, AWS Bedrock, services cognitifs
B8: 3 | C8: Hébergement web / messagerie
B9: 4 | C9: Sauvegarde cloud / réplication | D9: ● | G9: Détection d'anomalies, anti-ransomware IA
B11: Synthèse | E11: =COUNTA(E6:E9) -> 0 | F11: réponses sur 4 (dont 3 IA — 75%)
B13: ← Retour au sommaire

Sheet 5. Cybersécurité
B2: 5. Cybersécurité
B5: # | C5: Élément | D5: IA | E5: Réponse client | F5: Précision / autre | G5: Apport IA
B6: 1 | C6: Antivirus / EDR / XDR / SOC | D6: ● | G6: Détection comportementale, SOC augmenté
B7: 2 | C7: Pare-feu / filtrage web / anti-spam | D7: ● | G7: Filtrage IA, anti-phishing
B8: 3 | C8: Sauvegardes / PRA / PCA | D8: ● | G8: Détection ransomware par IA
B9: 4 | C9: MFA / SSO / IAM | D9: ● | G9: Analyse de risque adaptative
B10: 5 | C10: Gestion des mots de passe
B11: 6 | C11: Audits / pentests | D11: ● | G11: Outils IA d'analyse de vulnérabilités
B12: 7 | C12: Sensibilisation utilisateurs | D12: ● | G12: Simulations phishing IA, formations adaptatives
B13: 8 | C13: Conformité (RGPD, NIS 2, ISO 27001) | D13: ● | G13: Assistants de conformité IA
B15: Synthèse | E15: =COUNTA(E6:E13) -> 0 | F15: réponses sur 8 (dont 7 IA — 88%)
B17: ← Retour au sommaire

Sheet 6. Données & conformité
B2: 6. Données & conformité
B5: # | C5: Élément | D5: IA | E5: Réponse client | F5: Précision / autre | G5: Apport IA
B6: 1 | C6: BI / reporting / data | D6: ● | G6: Power BI Copilot, NL→SQL, prévisions
B7: 2 | C7: RGPD (registre, DPO) | D7: ● | G7: Assistants juridiques IA
B8: 3 | C8: Archivage à valeur probante | D8: ● | G8: Classification automatique
B9: 4 | C9: Facturation électronique (réforme 2026) | D9: ● | G9: Extraction et rapprochement IA
B10: 5 | C10: Mentions légales / CGU / CGV | D10: ● | G10: Génération assistée IA
B12: Synthèse | E12: =COUNTA(E6:E10) -> 0 | F12: réponses sur 5 (dont 5 IA — 100%)
B14: ← Retour au sommaire

Sheet 7. Présence en ligne & marketin
B2: 7. Présence en ligne & marketing
B5: # | C5: Élément | D5: IA | E5: Réponse client | F5: Précision / autre | G5: Apport IA
B6: 1 | C6: Nom de domaine
B7: 2 | C7: Site web / e-commerce | D7: ● | G7: Chatbots, recommandations, recherche IA
B8: 3 | C8: SEO / SEA / Google Business Profile | D8: ● | G8: Rédaction, analyse, optimisation IA
B9: 4 | C9: Réseaux sociaux | D9: ● | G9: Création de contenu et planification IA
B10: 5 | C10: Emailing / marketing automation | D10: ● | G10: Personnalisation, A/B testing IA
B12: Synthèse | E12: =COUNTA(E6:E10) -> 0 | F12: réponses sur 5 (dont 4 IA — 80%)
B14: ← Retour au sommaire

Sheet 8. Mobilité & télétravail
B2: 8. Mobilité & télétravail
B5: # | C5: Élément | D5: IA | E5: Réponse client | F5: Précision / autre | G5: Apport IA
B6: 1 | C6: Smartphones / tablettes pro | D6: ● | G6: Apple Intelligence, Galaxy AI
B7: 2 | C7: MDM / gestion de flotte | D7: ● | G7: Détection d'usage anormal
B8: 3 | C8: Accès distant sécurisé | D8: ● | G8: Scoring de risque IA
B9: 4 | C9: Postes nomades / virtualisation
B11: Synthèse | E11: =COUNTA(E6:E9) -> 0 | F11: réponses sur 4 (dont 3 IA — 75%)
B13: ← Retour au sommaire

Sheet 9. Services & exploitation
B2: 9. Services & exploitation
B5: # | C5: Élément | D5: IA | E5: Réponse client | F5: Précision / autre | G5: Apport IA
B6: 1 | C6: Infogérance / supervision | D6: ● | G6: AIOps, supervision prédictive
B7: 2 | C7: Help desk / support utilisateurs | D7: ● | G7: Agents IA niveau 1, copilotes techniciens
B8: 3 | C8: TMA | D8: ● | G8: Assistants de dev, génération de code
B9: 4 | C9: Patch management / MCO | D9: ● | G9: Priorisation IA des vulnérabilités
B10: 5 | C10: Gestion des licences / abonnements | D10: ● | G10: Optimisation, FinOps IA
B12: Synthèse | E12: =COUNTA(E6:E10) -> 0 | F12: réponses sur 5 (dont 5 IA — 100%)
B14: ← Retour au sommaire

Sheet 10. Innovation & transformation
B2: 10. Innovation & transformation
B5: # | C5: Élément | D5: IA | E5: Réponse client | F5: Précision / autre | G5: Apport IA
B6: 1 | C6: IA générative | D6: ● | G6: Cœur de l'offre IA
B7: 2 | C7: Automatisation / RPA / workflows | D7: ● | G7: Nœuds IA, agents autonomes
B8: 3 | C8: IoT / capteurs | D8: ● | G8: Maintenance prédictive
B9: 4 | C9: Dématérialisation des process | D9: ● | G9: Extraction et traitement IA
B11: Synthèse | E11: =COUNTA(E6:E9) -> 0 | F11: réponses sur 4 (dont 4 IA — 100%)
B13: ← Retour au sommaire

Sheet 11. Gouvernance & humain
B2: 11. Gouvernance & humain
B5: # | C5: Élément | D5: IA | E5: Réponse client | F5: Précision / autre | G5: Apport IA
B6: 1 | C6: Charte informatique / politique sécurité | D6: ● | G6: Charte IA, AI Act
B7: 2 | C7: Schéma directeur SI / budget IT
B8: 3 | C8: Formation / acculturation IA | D8: ● | G8: Formations IA personnalisées
B9: 4 | C9: Contrats SLA / RGPD / sous-traitance | D9: ● | G9: Analyse contractuelle IA
B11: Synthèse | E11: =COUNTA(E6:E9) -> 0 | F11: réponses sur 4 (dont 3 IA — 75%)
B13: ← Retour au sommaire
